opsys_spectrometer/__init__.py
opsys_spectrometer/avaspecx64.dll
opsys_spectrometer/spectrometer_abstract.py
opsys_spectrometer/spectrometer_controller.py
opsys_spectrometer-0.0.5.dist-info/LICENSE
opsys_spectrometer-0.0.5.dist-info/METADATA
opsys_spectrometer-0.0.5.dist-info/WHEEL
opsys_spectrometer-0.0.5.dist-info/top_level.txt
opsys_spectrometer-0.0.5.dist-info/RECORD
